MANIFEST.in
README.rst
requirements.txt
setup.cfg
setup.py
Docs/README.md
Docs/createdocs.py
Docs/docs/source/Makefile
Docs/docs/source/alignreadme.rst
Docs/docs/source/biosqlreadme.rst
Docs/docs/source/blastreadme.rst
Docs/docs/source/conf.py
Docs/docs/source/cookiesreadme.rst
Docs/docs/source/ftpreadme.rst
Docs/docs/source/genbankreadme.rst
Docs/docs/source/index.rst
Docs/docs/source/iqtreereadme.rst
Docs/docs/source/logitreadme.rst
Docs/docs/source/managerreadme.rst
Docs/docs/source/mpireadme.rst
Docs/docs/source/mygenereadme.rst
Docs/docs/source/orthoevolreadme.rst
Docs/docs/source/orthologsreadme.rst
Docs/docs/source/otherutilsreadme.rst
Docs/docs/source/pamlreadme.rst
Docs/docs/source/pandocreadme.rst
Docs/docs/source/parallelreadme.rst
Docs/docs/source/phylogeneticsreadme.rst
Docs/docs/source/phymlreadme.rst
Docs/docs/source/pipelinereadme.rst
Docs/docs/source/pybasherreadme.rst
Docs/docs/source/send2serverreadme.rst
Docs/docs/source/sgereadme.rst
Docs/docs/source/slackifyreadme.rst
Docs/docs/source/toolsreadme.rst
OrthoEvol/__init__.py
OrthoEvol.egg-info/PKG-INFO
OrthoEvol.egg-info/SOURCES.txt
OrthoEvol.egg-info/dependency_links.txt
OrthoEvol.egg-info/entry_points.txt
OrthoEvol.egg-info/not-zip-safe
OrthoEvol.egg-info/top_level.txt
OrthoEvol/Cookies/README.md
OrthoEvol/Cookies/__init__.py
OrthoEvol/Cookies/cookie_jar.py
OrthoEvol/Cookies/utils.py
OrthoEvol/Cookies/__pycache__/__init__.cpython-36.pyc
OrthoEvol/Cookies/__pycache__/cookie_jar.cpython-36.pyc
OrthoEvol/Cookies/__pycache__/utils.cpython-36.pyc
OrthoEvol/Cookies/new_app/cookiecutter.json
OrthoEvol/Cookies/new_app/hooks/new_app.py
OrthoEvol/Cookies/new_app/{{ cookiecutter.app_name }}/global.R
OrthoEvol/Cookies/new_app/{{ cookiecutter.app_name }}/index.html
OrthoEvol/Cookies/new_app/{{ cookiecutter.app_name }}/server.R
OrthoEvol/Cookies/new_app/{{ cookiecutter.app_name }}/ui.R
OrthoEvol/Cookies/new_app/{{ cookiecutter.app_name }}/data/.gitkeep
OrthoEvol/Cookies/new_app/{{ cookiecutter.app_name }}/scripts/.gitkeep
OrthoEvol/Cookies/new_app/{{ cookiecutter.app_name }}/tests/.gitkeep
OrthoEvol/Cookies/new_app/{{ cookiecutter.app_name }}/www/.gitkeep
