Metadata-Version: 1.1
Name: OrthoEvol
Version: 0.9.0a2
Summary: This package aids in the analysis of orthologous genes.
Home-page: https://github.com/datasnakes/OrthoEvolution
Author: Rob Gilmore & Shaurita Hutchins
Author-email: datasnakes@gmail.com
License: MIT
Keywords: bioinformatics science evolution orthology psychiatry genetics
Platform: UNKNOWN
Classifier: Development Status :: 3 - Alpha
Classifier: Intended Audience :: Science/Research
Classifier: Topic :: Scientific/Engineering :: Bio-Informatics
Classifier: Topic :: Scientific/Engineering :: Visualization
Classifier: Topic :: Scientific/Engineering :: Medical Science Apps.
Classifier: Programming Language :: Python :: 3
Classifier: Operating System :: POSIX :: Linux
Classifier: Operating System :: Unix
Classifier: Natural Language :: English
Classifier: Programming Language :: Python :: 3 :: Only
Classifier: Programming Language :: Python :: 3.5
Classifier: Programming Language :: Python :: 3.6
Classifier: Framework :: Flask
Classifier: Framework :: R-Shiny
Classifier: Framework :: Cookiecutter
